CHANGES.rst
CONTRIBUTORS.rst
DEVELOP.rst
LICENSE.rst
MANIFEST.in
README.rst
setup.cfg
setup.py
docs/conf.py
docs/index.rst
src/collective/__init__.py
src/collective.embedcontent.egg-info/PKG-INFO
src/collective.embedcontent.egg-info/SOURCES.txt
src/collective.embedcontent.egg-info/dependency_links.txt
src/collective.embedcontent.egg-info/entry_points.txt
src/collective.embedcontent.egg-info/namespace_packages.txt
src/collective.embedcontent.egg-info/not-zip-safe
src/collective.embedcontent.egg-info/requires.txt
src/collective.embedcontent.egg-info/top_level.txt
src/collective/embedcontent/__init__.py
src/collective/embedcontent/configure.zcml
src/collective/embedcontent/interfaces.py
src/collective/embedcontent/permissions.zcml
src/collective/embedcontent/setuphandlers.py
src/collective/embedcontent/testing.py
src/collective/embedcontent/upgrades.py
src/collective/embedcontent/upgrades.zcml
src/collective/embedcontent/browser/__init__.py
src/collective/embedcontent/browser/configure.zcml
src/collective/embedcontent/browser/embedcontent.py
src/collective/embedcontent/browser/embedcontenttile.pt
src/collective/embedcontent/browser/embedcontentview.pt
src/collective/embedcontent/browser/overrides/.gitkeep
src/collective/embedcontent/browser/static/.gitkeep
src/collective/embedcontent/browser/static/iframe.css
src/collective/embedcontent/browser/static/iframe.js
src/collective/embedcontent/content/__init__.py
src/collective/embedcontent/content/embedcontent.py
src/collective/embedcontent/locales/README.rst
src/collective/embedcontent/locales/__init__.py
src/collective/embedcontent/locales/collective.embedcontent.pot
src/collective/embedcontent/locales/update.py
src/collective/embedcontent/locales/update.sh
src/collective/embedcontent/locales/en/LC_MESSAGES/collective.embedcontent.po
src/collective/embedcontent/profiles/default/browserlayer.xml
src/collective/embedcontent/profiles/default/catalog.xml
src/collective/embedcontent/profiles/default/cssregistry.xml
src/collective/embedcontent/profiles/default/jsregistry.xml
src/collective/embedcontent/profiles/default/metadata.xml
src/collective/embedcontent/profiles/default/registry.xml
src/collective/embedcontent/profiles/default/rolemap.xml
src/collective/embedcontent/profiles/default/types.xml
src/collective/embedcontent/profiles/default/types/EmbedContent.xml
src/collective/embedcontent/profiles/uninstall/browserlayer.xml
